{
  "source": "toutiao_hot_board",
  "generated_at": "Tue, 14 Oct 2025 13:15:55 GMT",
  "top": {
    "rank": "置顶",
    "title": "共同谱写全球妇女事业发展新篇章",
    "url": "https://www.toutiao.com/article/7560742624253018687/",
    "label": ""
  },
  "items": [
    {
      "rank": 1,
      "title": "万科原总裁祝九胜已被控制",
      "url": "https://www.toutiao.com/trending/7560750260142915620/",
      "label": ""
    },
    {
      "rank": 2,
      "title": "京东11月9日发布新车",
      "url": "https://www.toutiao.com/trending/7560985618667277875/",
      "label": "hot"
    },
    {
      "rank": 3,
      "title": "6组数据看中国外贸强大韧性与活力",
      "url": "https://www.toutiao.com/article/7560892453880906240",
      "label": ""
    },
    {
      "rank": 4,
      "title": "公务员招录年龄放宽释放了什么信号",
      "url": "https://www.toutiao.com/trending/7559887861613903913/",
      "label": "interpretation"
    },
    {
      "rank": 5,
      "title": "如果欧美坚决不给中国飞机适航证咋办",
      "url": "https://www.toutiao.com/trending/7560742262495150107/",
      "label": "forum"
    },
    {
      "rank": 6,
      "title": "净网：网警带你看“网恋女友”杀熟局",
      "url": "https://www.toutiao.com/trending/7560861364386922538/",
      "label": ""
    },
    {
      "rank": 7,
      "title": "弟弟戴头巾掰玉米被姐姐误认成奶奶",
      "url": "https://www.toutiao.com/trending/7560649673644949546/",
      "label": "new"
    },
    {
      "rank": 8,
      "title": "小伙回应与农村老人拍低成本三国",
      "url": "https://www.toutiao.com/trending/7560857402120765494/",
      "label": "participant"
    },
    {
      "rank": 9,
      "title": "银行低利率下你选哪种理财方式",
      "url": "https://www.toutiao.com/trending/7560896985331548202/",
      "label": "forum"
    },
    {
      "rank": 10,
      "title": "玄奘法师铜像长满青苔？寺院辟谣",
      "url": "https://www.toutiao.com/trending/7560580718145929252/",
      "label": "refuteRumors"
    },
    {
      "rank": 11,
      "title": "演员李威出庭不认罪",
      "url": "https://www.toutiao.com/trending/7560910437485477931/",
      "label": "new"
    },
    {
      "rank": 12,
      "title": "婚礼当天跳河男子家属发声",
      "url": "https://www.toutiao.com/trending/7560855250731728915/",
      "label": "new"
    },
    {
      "rank": 13,
      "title": "荷兰回应“强制”接管中资芯片企业",
      "url": "https://www.toutiao.com/trending/7560929418953100851/",
      "label": "hot"
    },
    {
      "rank": 14,
      "title": "iPhone 17系列无法激活？苹果回应",
      "url": "https://www.toutiao.com/trending/7560947026498830374/",
      "label": "new"
    },
    {
      "rank": 15,
      "title": "京东回应推出新车：不直接涉及制造",
      "url": "https://www.toutiao.com/trending/7560972817052434495/",
      "label": "hot"
    },
    {
      "rank": 16,
      "title": "国考年龄放宽",
      "url": "https://www.toutiao.com/trending/7560714791988576310/",
      "label": "hot"
    },
    {
      "rank": 17,
      "title": "开豪车逃单你怎么看",
      "url": "https://www.toutiao.com/trending/7560967504034775049/",
      "label": "forum"
    },
    {
      "rank": 18,
      "title": "解清帅举办婚礼一天后奶奶离世",
      "url": "https://www.toutiao.com/trending/7560315933647142958/",
      "label": ""
    },
    {
      "rank": 19,
      "title": "武汉国企掷6382万买沥青遇空罐和水",
      "url": "https://www.toutiao.com/trending/7560964743436779546/",
      "label": ""
    },
    {
      "rank": 20,
      "title": "乒乓球亚锦赛女团：日本3-0新加坡",
      "url": "https://www.toutiao.com/trending/7560171183963602953/",
      "label": "new"
    },
    {
      "rank": 21,
      "title": "特朗普100%关税威胁是虚晃一枪吗",
      "url": "https://www.toutiao.com/trending/7560969100101422601/",
      "label": ""
    },
    {
      "rank": 22,
      "title": "金饰克价破1200元 年内已涨400元/克",
      "url": "https://www.toutiao.com/trending/7560207550243668010/",
      "label": "hot"
    },
    {
      "rank": 23,
      "title": "微信好友互删后互动清除",
      "url": "https://www.toutiao.com/trending/7560558146574549002/",
      "label": ""
    },
    {
      "rank": 24,
      "title": "谭松韵发文回应暴瘦",
      "url": "https://www.toutiao.com/trending/7560131990465298459/",
      "label": "new"
    },
    {
      "rank": 25,
      "title": "你用过“竹制十字裤架”吗",
      "url": "https://www.toutiao.com/trending/7560682756137697326/",
      "label": "new"
    },
    {
      "rank": 26,
      "title": "学者：我们不能掉进西方的傲慢",
      "url": "https://www.toutiao.com/trending/7559993293476560906/",
      "label": ""
    },
    {
      "rank": 27,
      "title": "业内：黄金价格仍然有上涨冲动",
      "url": "https://www.toutiao.com/trending/7561048370240818727/",
      "label": "interpretation"
    },
    {
      "rank": 28,
      "title": "特朗普C位合影喊话：大家笑起来",
      "url": "https://www.toutiao.com/trending/7560888494140182043/",
      "label": "onSite"
    },
    {
      "rank": 29,
      "title": "小伙被催婚后在山里失踪9天遇难",
      "url": "https://www.toutiao.com/trending/7560658493307600905/",
      "label": ""
    },
    {
      "rank": 30,
      "title": "郝龙斌公布两岸政策",
      "url": "https://www.toutiao.com/trending/7559988666887143462/",
      "label": "hot"
    },
    {
      "rank": 31,
      "title": "家中灶台爆炸 老人对着老伴遗像哭诉",
      "url": "https://www.toutiao.com/trending/7560919353819168814/",
      "label": ""
    },
    {
      "rank": 32,
      "title": "落马副部王波贪4.49亿余元被判死缓",
      "url": "https://www.toutiao.com/trending/7560999572689649702/",
      "label": ""
    },
    {
      "rank": 33,
      "title": "为何说巴基斯坦没有侵犯中国稀土技术",
      "url": "https://www.toutiao.com/trending/7560861413703634459/",
      "label": "interpretation"
    },
    {
      "rank": 34,
      "title": "十年后茅台股票和黄金谁更保值",
      "url": "https://www.toutiao.com/trending/7561001704406126090/",
      "label": ""
    },
    {
      "rank": 35,
      "title": "巴士兵使用步枪击倒阿富汗武装人员",
      "url": "https://www.toutiao.com/trending/7560868799365775411/",
      "label": "new"
    },
    {
      "rank": 36,
      "title": "辅警执勤时与骑车男子发生冲突被带离",
      "url": "https://www.toutiao.com/trending/7560993816975720490/",
      "label": "new"
    },
    {
      "rank": 37,
      "title": "“70后”省级政府一把手已有4人",
      "url": "https://www.toutiao.com/trending/7560997723730628106/",
      "label": ""
    },
    {
      "rank": 38,
      "title": "被主持人闭麦 万斯怒了",
      "url": "https://www.toutiao.com/trending/7560371535484141609/",
      "label": ""
    },
    {
      "rank": 39,
      "title": "年轻人热衷买黄金贴纸最低仅几十元",
      "url": "https://www.toutiao.com/trending/7561047720580877870/",
      "label": "new"
    },
    {
      "rank": 40,
      "title": "中国稀土：全球高端制造的命门",
      "url": "https://www.toutiao.com/trending/7560900818187062847/",
      "label": "interpretation"
    },
    {
      "rank": 41,
      "title": "向太谈小儿子向佑打人坐牢",
      "url": "https://www.toutiao.com/trending/7560867874924036150/",
      "label": ""
    },
    {
      "rank": 42,
      "title": "国乒女团获得伦敦世乒赛资格",
      "url": "https://www.toutiao.com/trending/7560277847735386163/",
      "label": ""
    },
    {
      "rank": 43,
      "title": "土耳其总统劝意总理戒烟逗乐马克龙",
      "url": "https://www.toutiao.com/trending/7560133313072414756/",
      "label": ""
    },
    {
      "rank": 44,
      "title": "青海网友拍下巨大管状物从天而降",
      "url": "https://www.toutiao.com/trending/7560945250374615076/",
      "label": "onSite"
    },
    {
      "rank": 45,
      "title": "黄金价格真的没有最高只有更高吗",
      "url": "https://www.toutiao.com/trending/7561047650854768178/",
      "label": "interpretation"
    },
    {
      "rank": 46,
      "title": "克林根：杨瀚森和我体型接近",
      "url": "https://www.toutiao.com/trending/7559975895084253235/",
      "label": "new"
    },
    {
      "rank": 47,
      "title": "17日至19日北京将现明显降温",
      "url": "https://www.toutiao.com/trending/7560715856830267431/",
      "label": "new"
    },
    {
      "rank": 48,
      "title": "国家开发银行原资深专家王学东被查",
      "url": "https://www.toutiao.com/trending/7561016182598451254/",
      "label": "new"
    },
    {
      "rank": 49,
      "title": "分立器件迎来“关键一天”",
      "url": "https://www.toutiao.com/trending/7560940907793485339/",
      "label": "hot"
    },
    {
      "rank": 50,
      "title": "今年雨水怎么这么多",
      "url": "https://www.toutiao.com/trending/7561047800356539958/",
      "label": "new"
    }
  ]
}