{
  "source": "toutiao_hot_board",
  "generated_at": "Mon, 13 Oct 2025 03:27:52 GMT",
  "top": {
    "rank": "置顶",
    "title": "总书记重要讲话指引妇女事业发展",
    "url": "https://www.toutiao.com/article/7560278592626721316/",
    "label": ""
  },
  "items": [
    {
      "rank": 1,
      "title": "特朗普释放信号：愿与中国达成协议",
      "url": "https://www.toutiao.com/trending/7560501650729733674/",
      "label": "hot"
    },
    {
      "rank": 2,
      "title": "美国强制下架数百万件中国电子产品",
      "url": "https://www.toutiao.com/trending/7560488115622661683/",
      "label": ""
    },
    {
      "rank": 3,
      "title": "开创城乡融合发展新局面",
      "url": "https://www.toutiao.com/article/7560495195800879654",
      "label": "new"
    },
    {
      "rank": 4,
      "title": "全台多名议长倒戈支持郑丽文",
      "url": "https://www.toutiao.com/trending/7559558013985488915/",
      "label": "new"
    },
    {
      "rank": 5,
      "title": "万科董事长辛杰辞职",
      "url": "https://www.toutiao.com/trending/7560498085282054195/",
      "label": ""
    },
    {
      "rank": 6,
      "title": "一个人长期不上班会变成什么样子",
      "url": "https://www.toutiao.com/trending/7560206583024992292/",
      "label": "forum"
    },
    {
      "rank": 7,
      "title": "唐驳虎：美国紧急给关税战灭火",
      "url": "https://www.toutiao.com/trending/7560490774882684442/",
      "label": "hot"
    },
    {
      "rank": 8,
      "title": "辛杰曾多次代表深铁力挺万科",
      "url": "https://www.toutiao.com/trending/7560512175631240754/",
      "label": ""
    },
    {
      "rank": 9,
      "title": "牛弹琴：巴阿大打出手 战况惨烈",
      "url": "https://www.toutiao.com/trending/7560488582012472851/",
      "label": ""
    },
    {
      "rank": 10,
      "title": "玉木雄一郎或捡漏成为日本新首相",
      "url": "https://www.toutiao.com/trending/7560508910608617011/",
      "label": "new"
    },
    {
      "rank": 11,
      "title": "男子造谣“村干部横行霸道”被罚",
      "url": "https://www.toutiao.com/trending/7560148012115673130/",
      "label": "refuteRumors"
    },
    {
      "rank": 12,
      "title": "宅基地可以继承吗",
      "url": "https://www.toutiao.com/trending/7560301831697252371/",
      "label": "forum"
    },
    {
      "rank": 13,
      "title": "航天游成中国文旅新热点",
      "url": "https://www.toutiao.com/trending/7560175627787010087/",
      "label": "new"
    },
    {
      "rank": 14,
      "title": "孩子考试进步考了61分全家欢呼",
      "url": "https://www.toutiao.com/trending/7560237182201757750/",
      "label": "onSite"
    },
    {
      "rank": 15,
      "title": "沈月与半裸男模对视捂脸低头笑",
      "url": "https://www.toutiao.com/trending/7560284583548321835/",
      "label": ""
    },
    {
      "rank": 16,
      "title": "美股期指集体反弹",
      "url": "https://www.toutiao.com/trending/7560480850865835529/",
      "label": ""
    },
    {
      "rank": 17,
      "title": "辛杰最近一次公开露面是8月底",
      "url": "https://www.toutiao.com/trending/7560507128944021042/",
      "label": ""
    },
    {
      "rank": 18,
      "title": "明星读EMBA是为了学知识还是混人脉",
      "url": "https://www.toutiao.com/trending/7560312848988373011/",
      "label": "forum"
    },
    {
      "rank": 19,
      "title": "万斯为何就中美关税博弈释放软调子",
      "url": "https://www.toutiao.com/trending/7560474861634604563/",
      "label": "interpretation"
    },
    {
      "rank": 20,
      "title": "广州公交站S型护栏拆除 官方致歉",
      "url": "https://www.toutiao.com/trending/7560178539581227051/",
      "label": ""
    },
    {
      "rank": 21,
      "title": "乒乓球团体亚锦赛日本男女团晋级四强",
      "url": "https://www.toutiao.com/trending/7560308716562710547/",
      "label": ""
    },
    {
      "rank": 22,
      "title": "普通人如何逃离币圈“财富绞肉机”",
      "url": "https://www.toutiao.com/trending/7560519398159552010/",
      "label": "new"
    },
    {
      "rank": 23,
      "title": "半年巨亏超百亿的万科何去何从",
      "url": "https://www.toutiao.com/trending/7560478911004413479/",
      "label": "interpretation"
    },
    {
      "rank": 24,
      "title": "巴基斯坦与阿富汗为什么突然打起来",
      "url": "https://www.toutiao.com/trending/7560522118148918825/",
      "label": "interpretation"
    },
    {
      "rank": 25,
      "title": "比特币向上升破115000美元",
      "url": "https://www.toutiao.com/trending/7560207426181316649/",
      "label": ""
    },
    {
      "rank": 26,
      "title": "李大霄：美股指夜期已经开始反弹",
      "url": "https://www.toutiao.com/trending/7560519486990716457/",
      "label": "new"
    },
    {
      "rank": 27,
      "title": "中美关系走到“死局”了吗",
      "url": "https://www.toutiao.com/trending/7560480328201014823/",
      "label": "interpretation"
    },
    {
      "rank": 28,
      "title": "台湾光复具有坚实的国际法基础",
      "url": "https://www.toutiao.com/trending/7560517808702885412/",
      "label": "new"
    },
    {
      "rank": 29,
      "title": "三大指数大幅低开",
      "url": "https://www.toutiao.com/trending/7559976933119983626/",
      "label": "new"
    },
    {
      "rank": 30,
      "title": "巴总理称将强硬回应巴阿边境冲突",
      "url": "https://www.toutiao.com/trending/7560225716777025599/",
      "label": ""
    },
    {
      "rank": 31,
      "title": "景区：趵突泉下没水泵但确有水管",
      "url": "https://www.toutiao.com/trending/7560484678663376435/",
      "label": ""
    },
    {
      "rank": 32,
      "title": "刘亦菲观看舞剧《天工开物》被偶遇",
      "url": "https://www.toutiao.com/trending/7560317704532803603/",
      "label": ""
    },
    {
      "rank": 33,
      "title": "特朗普犹太裔女婿现身加沙",
      "url": "https://www.toutiao.com/trending/7560074397462151231/",
      "label": ""
    },
    {
      "rank": 34,
      "title": "黄河出现2025年第1号洪水",
      "url": "https://www.toutiao.com/trending/7560509332723371558/",
      "label": ""
    },
    {
      "rank": 35,
      "title": "万科新董事长黄力平是何许人也",
      "url": "https://www.toutiao.com/trending/7560522283630988836/",
      "label": "new"
    },
    {
      "rank": 36,
      "title": "以色列总理称仍面临重大安全挑战",
      "url": "https://www.toutiao.com/trending/7560177572546494514/",
      "label": ""
    },
    {
      "rank": 37,
      "title": "神秘交易员再度开出1.6亿美元空单",
      "url": "https://www.toutiao.com/trending/7560512876289461802/",
      "label": "new"
    },
    {
      "rank": 38,
      "title": "知名高校学子投身军营",
      "url": "https://www.toutiao.com/trending/7560493225120170025/",
      "label": "new"
    },
    {
      "rank": 39,
      "title": "四川地震男子秒跑又折返抱娃",
      "url": "https://www.toutiao.com/trending/7560206221991575593/",
      "label": "onSite"
    },
    {
      "rank": 40,
      "title": "男子称亏妻者百事不顺",
      "url": "https://www.toutiao.com/trending/7560269258698768394/",
      "label": "new"
    },
    {
      "rank": 41,
      "title": "西安的雨把城墙都下绿了",
      "url": "https://www.toutiao.com/trending/7560179363858300969/",
      "label": ""
    },
    {
      "rank": 42,
      "title": "郝龙斌暗指卢秀燕挺他出来参选",
      "url": "https://www.toutiao.com/trending/7559830222561443876/",
      "label": "new"
    },
    {
      "rank": 43,
      "title": "美智库称对付中国韩没有日“趁手”",
      "url": "https://www.toutiao.com/trending/7560495125328367147/",
      "label": ""
    },
    {
      "rank": 44,
      "title": "NBA主场首秀 队友夸杨瀚森不一般",
      "url": "https://www.toutiao.com/trending/7560477586300603958/",
      "label": ""
    },
    {
      "rank": 45,
      "title": "母子俩拍回忆杀 网友误以为夫妻",
      "url": "https://www.toutiao.com/trending/7560178880804438026/",
      "label": ""
    },
    {
      "rank": 46,
      "title": "美国有哪些可以限制中国的稀有资源",
      "url": "https://www.toutiao.com/trending/7560502375685852714/",
      "label": "new"
    },
    {
      "rank": 47,
      "title": "周杰伦自曝有时会恐慌发作无法上台",
      "url": "https://www.toutiao.com/trending/7560344316724887593/",
      "label": ""
    },
    {
      "rank": 48,
      "title": "《沉默的荣耀》杨斯塑造鲜活窦太太",
      "url": "https://www.toutiao.com/trending/7560209872672210987/",
      "label": "new"
    },
    {
      "rank": 49,
      "title": "中国海警公布菲船只侵闯铁线礁视频",
      "url": "https://www.toutiao.com/trending/7560479077866409513/",
      "label": ""
    },
    {
      "rank": 50,
      "title": "苏超淘汰球队喊话明年再战：全是世仇",
      "url": "https://www.toutiao.com/trending/7560209952401326089/",
      "label": ""
    }
  ]
}