{
  "source": "toutiao_hot_board",
  "generated_at": "Thu, 30 Oct 2025 06:10:05 GMT",
  "top": {
    "rank": "置顶",
    "title": "从习主席的APEC足迹感悟中国智慧",
    "url": "https://www.toutiao.com/article/7566627168215466532/",
    "label": ""
  },
  "items": [
    {
      "rank": 1,
      "title": "中美元首握手合影",
      "url": "https://www.toutiao.com/video/7566852947381109263",
      "label": "onSite"
    },
    {
      "rank": 2,
      "title": "中美元首会晤开场白传递哪些重磅信息",
      "url": "https://www.toutiao.com/article/7566863096615043603",
      "label": "interpretation"
    },
    {
      "rank": 3,
      "title": "这就是APEC",
      "url": "https://www.toutiao.com/article/7566653862724928041",
      "label": ""
    },
    {
      "rank": 4,
      "title": "两名港澳航天员整体状态良好",
      "url": "https://www.toutiao.com/trending/7566826002874793990/",
      "label": "hot"
    },
    {
      "rank": 5,
      "title": "特朗普：相信我们将建立长期良好关系",
      "url": "https://www.toutiao.com/article/7566842915004219904",
      "label": "hot"
    },
    {
      "rank": 6,
      "title": "净网：网民编造有人跳桥失踪被查处",
      "url": "https://www.toutiao.com/trending/7566808721708469811/",
      "label": ""
    },
    {
      "rank": 7,
      "title": "如何看待美国削减北约东翼驻军",
      "url": "https://www.toutiao.com/trending/7566594487733043246/",
      "label": "forum"
    },
    {
      "rank": 8,
      "title": "中美携手多办一些大事实事好事",
      "url": "https://www.toutiao.com/article/7566836696604508715",
      "label": "hot"
    },
    {
      "rank": 9,
      "title": "速览“十五五”时期发展重要着力点",
      "url": "https://www.toutiao.com/article/7566643783924777523",
      "label": ""
    },
    {
      "rank": 10,
      "title": "国安披露东海小组4人烈士证明",
      "url": "https://www.toutiao.com/trending/7566200777514532902/",
      "label": ""
    },
    {
      "rank": 11,
      "title": "贵阳出租车起步价降至7元？协会辟谣",
      "url": "https://www.toutiao.com/trending/7565892844188270611/",
      "label": "refuteRumors"
    },
    {
      "rank": 12,
      "title": "女子将黄金手镯皮带涂成银色入境被查",
      "url": "https://www.toutiao.com/trending/7566823557318164499/",
      "label": "new"
    },
    {
      "rank": 13,
      "title": "女子被外国人占卧铺 12306：无需妥协",
      "url": "https://www.toutiao.com/trending/7566863777568869939/",
      "label": ""
    },
    {
      "rank": 14,
      "title": "报告：特朗普在自导自演贸易战中败北",
      "url": "https://www.toutiao.com/trending/7566831598922894890/",
      "label": "new"
    },
    {
      "rank": 15,
      "title": "你会让孩子参加竞赛活动吗",
      "url": "https://www.toutiao.com/trending/7566563944098693129/",
      "label": "forum"
    },
    {
      "rank": 16,
      "title": "女生晒干会计前后对比照判若两人",
      "url": "https://www.toutiao.com/trending/7566082784868352041/",
      "label": ""
    },
    {
      "rank": 17,
      "title": "中科院85后博导将逐梦太空 姐姐发声",
      "url": "https://www.toutiao.com/trending/7566661509154164260/",
      "label": "hot"
    },
    {
      "rank": 18,
      "title": "牛弹琴：韩国人讨好特朗普用心良苦",
      "url": "https://www.toutiao.com/trending/7566841369273729043/",
      "label": "new"
    },
    {
      "rank": 19,
      "title": "男子做完足疗从消防通道逃单",
      "url": "https://www.toutiao.com/trending/7566637901522993171/",
      "label": ""
    },
    {
      "rank": 20,
      "title": "我国正式启动巴基斯坦航天员选拔工作",
      "url": "https://www.toutiao.com/trending/7566819562147741715/",
      "label": "new"
    },
    {
      "rank": 21,
      "title": "江一燕离婚",
      "url": "https://www.toutiao.com/trending/7566884351229578802/",
      "label": "new"
    },
    {
      "rank": 22,
      "title": "里夫斯压哨绝杀 湖人险胜森林狼",
      "url": "https://www.toutiao.com/trending/7566864637015428671/",
      "label": "hot"
    },
    {
      "rank": 23,
      "title": "神二十乘组有望刷新在轨驻留最长纪录",
      "url": "https://www.toutiao.com/trending/7566134677032190006/",
      "label": "hot"
    },
    {
      "rank": 24,
      "title": "古巴外长打断美方发言：这不是聊天群",
      "url": "https://www.toutiao.com/trending/7566812004518956582/",
      "label": "onSite"
    },
    {
      "rank": 25,
      "title": "杭州一些稻田现大量“瑞士卷”",
      "url": "https://www.toutiao.com/trending/7566034030547501107/",
      "label": ""
    },
    {
      "rank": 26,
      "title": "神21出征当天是钱学森逝世纪念日",
      "url": "https://www.toutiao.com/trending/7566812847674605611/",
      "label": "hot"
    },
    {
      "rank": 27,
      "title": "美国为何每年花费巨资进口原油",
      "url": "https://www.toutiao.com/trending/7566833134012993067/",
      "label": "new"
    },
    {
      "rank": 28,
      "title": "郑丽文回应朱立伦带211名干部辞职",
      "url": "https://www.toutiao.com/trending/7566646268962065970/",
      "label": "hot"
    },
    {
      "rank": 29,
      "title": "中国年龄最小的航天员",
      "url": "https://www.toutiao.com/trending/7566831912782859814/",
      "label": ""
    },
    {
      "rank": 30,
      "title": "中国元首外交为何落子亚太",
      "url": "https://www.toutiao.com/trending/7566609518960902153/",
      "label": "interpretation"
    },
    {
      "rank": 31,
      "title": "王暖暖前夫被曝系电诈人员",
      "url": "https://www.toutiao.com/trending/7566078790129729572/",
      "label": ""
    },
    {
      "rank": 32,
      "title": "神二十一航天员名单公布",
      "url": "https://www.toutiao.com/trending/7566456049532813354/",
      "label": ""
    },
    {
      "rank": 33,
      "title": "德国外长取消访华后解释：我还想来",
      "url": "https://www.toutiao.com/trending/7565828087310008326/",
      "label": ""
    },
    {
      "rank": 34,
      "title": "云南BIGBANG近7天涨粉超72万",
      "url": "https://www.toutiao.com/trending/7566086090793631807/",
      "label": ""
    },
    {
      "rank": 35,
      "title": "航天员张陆谈重返太空过新年",
      "url": "https://www.toutiao.com/trending/7566833300598947850/",
      "label": "new"
    },
    {
      "rank": 36,
      "title": "美联储再降息25基点",
      "url": "https://www.toutiao.com/trending/7565851138500788251/",
      "label": ""
    },
    {
      "rank": 37,
      "title": "“欢喜哥”这个角色为何深入人心",
      "url": "https://www.toutiao.com/trending/7566541763091910207/",
      "label": ""
    },
    {
      "rank": 38,
      "title": "神舟二十号航天员乘组将回家",
      "url": "https://www.toutiao.com/trending/7566828140333662214/",
      "label": ""
    },
    {
      "rank": 39,
      "title": "6名巴基斯坦士兵在一次行动中身亡",
      "url": "https://www.toutiao.com/trending/7566164632919015462/",
      "label": "new"
    },
    {
      "rank": 40,
      "title": "德机构：中国已在所有领域冲击美优势",
      "url": "https://www.toutiao.com/trending/7566811934054419994/",
      "label": ""
    },
    {
      "rank": 41,
      "title": "4只小鼠将上太空",
      "url": "https://www.toutiao.com/trending/7566661509154098724/",
      "label": ""
    },
    {
      "rank": 42,
      "title": "杜兰特19中11砍31分5板3帽",
      "url": "https://www.toutiao.com/trending/7565825899166269459/",
      "label": ""
    },
    {
      "rank": 43,
      "title": "落马女副厅被逮捕 外号“田哥艳姐”",
      "url": "https://www.toutiao.com/trending/7566551088485417002/",
      "label": ""
    },
    {
      "rank": 44,
      "title": "武飞：让太空的中国年成为人生记忆",
      "url": "https://www.toutiao.com/trending/7566464484588601398/",
      "label": "new"
    },
    {
      "rank": 45,
      "title": "美对韩汽车关税降至15%",
      "url": "https://www.toutiao.com/trending/7566783375056899638/",
      "label": ""
    },
    {
      "rank": 46,
      "title": "普京：海燕导弹启动时间短且射程无限",
      "url": "https://www.toutiao.com/trending/7566063840555794459/",
      "label": "new"
    },
    {
      "rank": 47,
      "title": "解码神舟二十一号任务标识",
      "url": "https://www.toutiao.com/trending/7566295565437829183/",
      "label": "new"
    },
    {
      "rank": 48,
      "title": "8名木工赴柬埔寨务工被转卖",
      "url": "https://www.toutiao.com/trending/7565863907135324203/",
      "label": ""
    },
    {
      "rank": 49,
      "title": "黄磊：我每年都在乌镇多待一天",
      "url": "https://www.toutiao.com/trending/7566809747454692905/",
      "label": "new"
    },
    {
      "rank": 50,
      "title": "有1套舱外服即将“退休”",
      "url": "https://www.toutiao.com/trending/7566591604056686598/",
      "label": ""
    }
  ]
}