{
  "source": "toutiao_hot_board",
  "generated_at": "Mon, 29 Sep 2025 01:40:04 GMT",
  "top": {
    "rank": "置顶",
    "title": "习近平对党校工作作出重要指示",
    "url": "https://www.toutiao.com/article/7555084428293358120/",
    "label": ""
  },
  "items": [
    {
      "rank": 1,
      "title": "女子被骗百万卖家里3套房 父母崩溃",
      "url": "https://www.toutiao.com/trending/7554792200194785322/",
      "label": ""
    },
    {
      "rank": 2,
      "title": "九三阅兵礼宾车正陆续返还车主",
      "url": "https://www.toutiao.com/trending/7554298692568776747/",
      "label": ""
    },
    {
      "rank": 3,
      "title": "中国多领域经济亮点频现",
      "url": "https://www.toutiao.com/article/7555042334656889407",
      "label": ""
    },
    {
      "rank": 4,
      "title": "美军五天四射洲际导弹有何意图",
      "url": "https://www.toutiao.com/trending/7554875557093081142/",
      "label": "interpretation"
    },
    {
      "rank": 5,
      "title": "你会因哪些原因想离职",
      "url": "https://www.toutiao.com/trending/7554969260214992915/",
      "label": "forum"
    },
    {
      "rank": 6,
      "title": "大爷拦婚车靠在劳斯莱斯车头不走",
      "url": "https://www.toutiao.com/trending/7554932819647021066/",
      "label": ""
    },
    {
      "rank": 7,
      "title": "国民党主席选举已选边站？洪秀柱驳斥",
      "url": "https://www.toutiao.com/trending/7554314653069754410/",
      "label": "hot"
    },
    {
      "rank": 8,
      "title": "游客称在景区遭遇21474836元停车费",
      "url": "https://www.toutiao.com/trending/7554401730654552118/",
      "label": "new"
    },
    {
      "rank": 9,
      "title": "王力宏独唱《心中的日月》",
      "url": "https://www.toutiao.com/trending/7554200860931588106/",
      "label": "new"
    },
    {
      "rank": 10,
      "title": "打工人将迎来最轻松10月",
      "url": "https://www.toutiao.com/trending/7554264776358658089/",
      "label": ""
    },
    {
      "rank": 11,
      "title": "城管执法时掀水果摊打人？官方辟谣",
      "url": "https://www.toutiao.com/trending/7555286116438494771/",
      "label": "refuteRumors"
    },
    {
      "rank": 12,
      "title": "华南理工遇难女生当天过18岁生日",
      "url": "https://www.toutiao.com/trending/7555133075987431450/",
      "label": ""
    },
    {
      "rank": 13,
      "title": "王健林限高措施已取消",
      "url": "https://www.toutiao.com/trending/7555305854099279369/",
      "label": "recentProgress"
    },
    {
      "rank": 14,
      "title": "沈佳润出场 小沈阳被抬走",
      "url": "https://www.toutiao.com/trending/7554121459904544822/",
      "label": ""
    },
    {
      "rank": 15,
      "title": "专家：房价下跌最吃亏的是普通老百姓",
      "url": "https://www.toutiao.com/trending/7555286355706646079/",
      "label": "interpretation"
    },
    {
      "rank": 16,
      "title": "家用电器存安全隐患有多危险",
      "url": "https://www.toutiao.com/trending/7555043611386789951/",
      "label": "forum"
    },
    {
      "rank": 17,
      "title": "闫妮“微醺”气质传染魏大勋",
      "url": "https://www.toutiao.com/trending/7555146716090548267/",
      "label": ""
    },
    {
      "rank": 18,
      "title": "邓超坐轮椅宣传电影",
      "url": "https://www.toutiao.com/trending/7555101039944945206/",
      "label": ""
    },
    {
      "rank": 19,
      "title": "女生上台表演被演员扯摔在地上",
      "url": "https://www.toutiao.com/trending/7555061398242787371/",
      "label": ""
    },
    {
      "rank": 20,
      "title": "解晓东小酒窝合唱《中国娃》",
      "url": "https://www.toutiao.com/trending/7555274553506201609/",
      "label": ""
    },
    {
      "rank": 21,
      "title": "甘肃本次地震震动有多猛烈",
      "url": "https://www.toutiao.com/trending/7555279686905892415/",
      "label": ""
    },
    {
      "rank": 22,
      "title": "英媒记者要求俄外长用英语回答被拒",
      "url": "https://www.toutiao.com/trending/7555070936295296539/",
      "label": ""
    },
    {
      "rank": 23,
      "title": "评论员：特朗普决心向美军“开刀”",
      "url": "https://www.toutiao.com/trending/7554212610854354963/",
      "label": "interpretation"
    },
    {
      "rank": 24,
      "title": "佟丽娅和儿子合唱《世上只有妈妈好》",
      "url": "https://www.toutiao.com/trending/7554901995094753316/",
      "label": ""
    },
    {
      "rank": 25,
      "title": "周深深情演唱《故乡的云》",
      "url": "https://www.toutiao.com/trending/7554501442179072041/",
      "label": ""
    },
    {
      "rank": 26,
      "title": "吴艳妮强势夺冠后复盘称还是很差",
      "url": "https://www.toutiao.com/trending/7554658175396872231/",
      "label": ""
    },
    {
      "rank": 27,
      "title": "韩国游行民众向内塔尼亚胡海报扔鞋",
      "url": "https://www.toutiao.com/trending/7555098059978559002/",
      "label": ""
    },
    {
      "rank": 28,
      "title": "王楚钦赢球后与王皓儿子击掌",
      "url": "https://www.toutiao.com/trending/7554687159807066131/",
      "label": "new"
    },
    {
      "rank": 29,
      "title": "80岁台湾歌手凌峰演唱《吾爱吾国》",
      "url": "https://www.toutiao.com/trending/7555148575191056438/",
      "label": ""
    },
    {
      "rank": 30,
      "title": "王楚钦爆冲球速75公里每小时",
      "url": "https://www.toutiao.com/trending/7554281266607390762/",
      "label": "onSite"
    },
    {
      "rank": 31,
      "title": "美国与委内瑞拉谁更怕擦枪走火",
      "url": "https://www.toutiao.com/trending/7554322596423093801/",
      "label": "depth"
    },
    {
      "rank": 32,
      "title": "徐怀钰周洁琼合唱《踏浪》",
      "url": "https://www.toutiao.com/trending/7554183562950901823/",
      "label": ""
    },
    {
      "rank": 33,
      "title": "环保少女再赴加沙获多国海军支援",
      "url": "https://www.toutiao.com/trending/7553986129352785929/",
      "label": ""
    },
    {
      "rank": 34,
      "title": "千万身家男子亲妈专程感谢河南养母",
      "url": "https://webcast-open.douyin.com/open/media_live/684938926972",
      "label": "new"
    },
    {
      "rank": 35,
      "title": "福建舰电磁弹射的战略突破影响几何",
      "url": "https://www.toutiao.com/trending/7555288654319619594/",
      "label": ""
    },
    {
      "rank": 36,
      "title": "吴艳妮12秒90夺冠",
      "url": "https://www.toutiao.com/trending/7554604134587121700/",
      "label": ""
    },
    {
      "rank": 37,
      "title": "鸡排哥发声感谢网友关心",
      "url": "https://www.toutiao.com/trending/7554403449916637238/",
      "label": "participant"
    },
    {
      "rank": 38,
      "title": "美企CEO担忧特朗普掏空美国经济",
      "url": "https://www.toutiao.com/trending/7555125940817235507/",
      "label": ""
    },
    {
      "rank": 39,
      "title": "王毅会见朝鲜外相崔善姬有何看点",
      "url": "https://www.toutiao.com/trending/7555280382141156914/",
      "label": "interpretation"
    },
    {
      "rank": 40,
      "title": "王暖暖离婚为何这么难",
      "url": "https://www.toutiao.com/trending/7553947654335004708/",
      "label": "interpretation"
    },
    {
      "rank": 41,
      "title": "媒体：依法惩治讹人者匡扶世道人心",
      "url": "https://www.toutiao.com/trending/7554678206440718379/",
      "label": ""
    },
    {
      "rank": 42,
      "title": "美军为何在加勒比海频繁活动",
      "url": "https://www.toutiao.com/trending/7554322596423061033/",
      "label": "interpretation"
    },
    {
      "rank": 43,
      "title": "“出差遭老板性侵”当事人怒怼网友",
      "url": "https://www.toutiao.com/trending/7554170643772686355/",
      "label": ""
    },
    {
      "rank": 44,
      "title": "特朗普B计划激进施压俄实为洗手不干",
      "url": "https://www.toutiao.com/trending/7555279803826310683/",
      "label": ""
    },
    {
      "rank": 45,
      "title": "中国大满贯：孙颖莎王楚钦迎开门红",
      "url": "https://www.toutiao.com/trending/7555035541209808950/",
      "label": "new"
    },
    {
      "rank": 46,
      "title": "正部级“老虎”唐仁健贪2.68亿获死缓",
      "url": "https://www.toutiao.com/trending/7555062194414108715/",
      "label": ""
    },
    {
      "rank": 47,
      "title": "俄称别尔哥罗德州再遭袭",
      "url": "https://www.toutiao.com/trending/7555008253366075442/",
      "label": "new"
    },
    {
      "rank": 48,
      "title": "哥伦比亚总统为何称联合国应搬离纽约",
      "url": "https://www.toutiao.com/trending/7555281764638281252/",
      "label": ""
    },
    {
      "rank": 49,
      "title": "湘超湘潭主场万人合唱《东方红》",
      "url": "https://www.toutiao.com/trending/7555101039944912438/",
      "label": ""
    },
    {
      "rank": 50,
      "title": "哈马斯称尚未收到新的停火提案",
      "url": "https://www.toutiao.com/trending/7554369064271724590/",
      "label": "new"
    }
  ]
}