{
  "source": "toutiao_hot_board",
  "generated_at": "Sat, 18 Oct 2025 07:15:04 GMT",
  "top": {
    "rank": "置顶",
    "title": "非凡十四五 美丽中国铺展新画卷",
    "url": "https://www.toutiao.com/article/7562314862030799398/",
    "label": ""
  },
  "items": [
    {
      "rank": 1,
      "title": "泽连斯基可能得再次从头说服特朗普",
      "url": "https://www.toutiao.com/trending/7561736617245838889/",
      "label": "hot"
    },
    {
      "rank": 2,
      "title": "国民党今日选出新主席",
      "url": "https://www.toutiao.com/trending/7562372211441405450/",
      "label": "hot"
    },
    {
      "rank": 3,
      "title": "红星照耀中国",
      "url": "https://www.toutiao.com/article/7562084246334669339",
      "label": ""
    },
    {
      "rank": 4,
      "title": "新能源车火灾事故报告制度有何考量",
      "url": "https://www.toutiao.com/trending/7562100193659850290/",
      "label": ""
    },
    {
      "rank": 5,
      "title": "台媒体人：郑丽文当选几率大",
      "url": "https://www.toutiao.com/trending/7561596274517229609/",
      "label": "hot"
    },
    {
      "rank": 6,
      "title": "护网|WannaCry勒索风暴警示与防范",
      "url": "https://www.toutiao.com/trending/7561996253900931111/",
      "label": ""
    },
    {
      "rank": 7,
      "title": "杨振宁逝世",
      "url": "https://api.toutiaoapi.com/feoffline/amos_subject/hotrio_subject_page_h5/html/main/index.html",
      "label": "amos"
    },
    {
      "rank": 8,
      "title": "清华大学悼念杨振宁",
      "url": "https://www.toutiao.com/trending/7562414698142895658/",
      "label": "hot"
    },
    {
      "rank": 9,
      "title": "近期降温对秋收秋种有什么影响",
      "url": "https://www.toutiao.com/trending/7561736617245871657/",
      "label": ""
    },
    {
      "rank": 10,
      "title": "天津新能源车辆将限号？假的",
      "url": "https://www.toutiao.com/trending/7562127046933970995/",
      "label": "refuteRumors"
    },
    {
      "rank": 11,
      "title": "杨振宁刚刚过完103岁生日",
      "url": "https://www.toutiao.com/trending/7562415604024475694/",
      "label": "hot"
    },
    {
      "rank": 12,
      "title": "你会花高价买“袖珍牛”吗",
      "url": "https://www.toutiao.com/trending/7562214071019159602/",
      "label": "forum"
    },
    {
      "rank": 13,
      "title": "你如何看待孩子帮忙看店卖货",
      "url": "https://www.toutiao.com/trending/7562168006589710375/",
      "label": "forum"
    },
    {
      "rank": 14,
      "title": "杨振宁的三次告别",
      "url": "https://www.toutiao.com/trending/7562431947440639534/",
      "label": "hot"
    },
    {
      "rank": 15,
      "title": "台专家谈《沉默的荣耀》",
      "url": "https://www.toutiao.com/trending/7561978946678636586/",
      "label": "hot"
    },
    {
      "rank": 16,
      "title": "英伟达退出 国产AI芯片要崛起了吗",
      "url": "https://www.toutiao.com/trending/7562416129633701419/",
      "label": ""
    },
    {
      "rank": 17,
      "title": "4分钟回顾杨振宁一生",
      "url": "https://www.toutiao.com/trending/7562424027206372902/",
      "label": "hot"
    },
    {
      "rank": 18,
      "title": "专家：三大替代市场成中国出口关键",
      "url": "https://www.toutiao.com/trending/7562401615076920841/",
      "label": "interpretation"
    },
    {
      "rank": 19,
      "title": "欧洲车企呼吁解决芯片供应问题",
      "url": "https://www.toutiao.com/trending/7562400627268013607/",
      "label": ""
    },
    {
      "rank": 20,
      "title": "杨振宁曾谈高龄恢复中国籍：很高兴",
      "url": "https://www.toutiao.com/trending/7562437235438816819/",
      "label": ""
    },
    {
      "rank": 21,
      "title": "黄金白银大跳水",
      "url": "https://www.toutiao.com/trending/7561551906565259273/",
      "label": ""
    },
    {
      "rank": 22,
      "title": "小S得奖后泪崩",
      "url": "https://www.toutiao.com/trending/7562350594041036836/",
      "label": "new"
    },
    {
      "rank": 23,
      "title": "杨振宁曾说最大贡献是助中国人自信",
      "url": "https://www.toutiao.com/trending/7562423842925186623/",
      "label": ""
    },
    {
      "rank": 24,
      "title": "辽宁4岁女童在病床上感谢大家",
      "url": "https://www.toutiao.com/trending/7562059135173492790/",
      "label": "new"
    },
    {
      "rank": 25,
      "title": "张亚中：台湾头上的堰塞湖随时会崩掉",
      "url": "https://www.toutiao.com/trending/7561981650830164031/",
      "label": ""
    },
    {
      "rank": 26,
      "title": "杨振宁生前说邓稼先会满意的",
      "url": "https://www.toutiao.com/trending/7561686857801826355/",
      "label": "new"
    },
    {
      "rank": 27,
      "title": "美国纪录片预告：核设施上空现UFO",
      "url": "https://www.toutiao.com/trending/7562161809495670794/",
      "label": ""
    },
    {
      "rank": 28,
      "title": "特朗普为何在对华关税问题上态度变软",
      "url": "https://www.toutiao.com/trending/7562386513762192937/",
      "label": ""
    },
    {
      "rank": 29,
      "title": "西湖大学悼念杨振宁 官网已变黑白",
      "url": "https://www.toutiao.com/trending/7562172508456402954/",
      "label": ""
    },
    {
      "rank": 30,
      "title": "江西小伙回应丈母娘拒收彩礼",
      "url": "https://www.toutiao.com/trending/7561861070715535414/",
      "label": ""
    },
    {
      "rank": 31,
      "title": "中方反制见效：首艘美船只被罚446万",
      "url": "https://www.toutiao.com/trending/7561666500550164523/",
      "label": ""
    },
    {
      "rank": 32,
      "title": "杨振宁逝世：宇宙无声但有繁星回答",
      "url": "https://www.toutiao.com/trending/7562437138042588714/",
      "label": "depth"
    },
    {
      "rank": 33,
      "title": "具俊晔每天画大S画像",
      "url": "https://www.toutiao.com/trending/7561683943771308074/",
      "label": ""
    },
    {
      "rank": 34,
      "title": "巴军空袭阿边境打死至少70名武装人员",
      "url": "https://www.toutiao.com/trending/7561282488405557290/",
      "label": ""
    },
    {
      "rank": 35,
      "title": "杨振宁逝世：一个世纪的传奇谢幕",
      "url": "https://www.toutiao.com/trending/7562432295001394714/",
      "label": "depth"
    },
    {
      "rank": 36,
      "title": "曹德旺交班给儿子 捐出1/3财富建大学",
      "url": "https://www.toutiao.com/trending/7561963971856023579/",
      "label": ""
    },
    {
      "rank": 37,
      "title": "女博主诉马夫性骚扰案下月将开庭",
      "url": "https://www.toutiao.com/trending/7562195429602279467/",
      "label": ""
    },
    {
      "rank": 38,
      "title": "媒体：杨振宁的家国情怀令人感佩",
      "url": "https://www.toutiao.com/trending/7562432100318580266/",
      "label": "new"
    },
    {
      "rank": 39,
      "title": "普京特使提议建普京-特朗普隧道",
      "url": "https://www.toutiao.com/trending/7561908833744879652/",
      "label": "new"
    },
    {
      "rank": 40,
      "title": "发68页PPT举报妻子出轨当事人发声",
      "url": "https://www.toutiao.com/trending/7561532297326133299/",
      "label": ""
    },
    {
      "rank": 41,
      "title": "杨振宁去世：一个世纪的探索与乡愁",
      "url": "https://www.toutiao.com/trending/7562435754526248498/",
      "label": "depth"
    },
    {
      "rank": 42,
      "title": "如何看待普京主动邀约特朗普调停",
      "url": "https://www.toutiao.com/trending/7562010479171715115/",
      "label": "interpretation"
    },
    {
      "rank": 43,
      "title": "福州市市长调研吴石故居",
      "url": "https://www.toutiao.com/trending/7562395997306011686/",
      "label": "new"
    },
    {
      "rank": 44,
      "title": "杨振宁：我身体里循环着中华文化血液",
      "url": "https://www.toutiao.com/trending/7562425479819693578/",
      "label": ""
    },
    {
      "rank": 45,
      "title": "9月份稀土及其制品出口10538吨",
      "url": "https://www.toutiao.com/trending/7562095382335864882/",
      "label": "new"
    },
    {
      "rank": 46,
      "title": "金价继续冲击新高",
      "url": "https://www.toutiao.com/trending/7562389196388716068/",
      "label": ""
    },
    {
      "rank": 47,
      "title": "杨振宁13岁时就立志要拿诺贝尔奖",
      "url": "https://www.toutiao.com/trending/7561961884165865515/",
      "label": ""
    },
    {
      "rank": 48,
      "title": "网红公开指责女演员后道歉",
      "url": "https://www.toutiao.com/trending/7562328982377513003/",
      "label": ""
    },
    {
      "rank": 49,
      "title": "上海一中学通报两名学生在教室争执",
      "url": "https://www.toutiao.com/trending/7562097529732038695/",
      "label": "new"
    },
    {
      "rank": 50,
      "title": "杨振宁精神与中国科学“千里共同途”",
      "url": "https://www.toutiao.com/trending/7562441906454548014/",
      "label": "new"
    }
  ]
}