{
  "source": "toutiao_hot_board",
  "generated_at": "Tue, 25 Nov 2025 04:29:39 GMT",
  "top": {
    "rank": "置顶",
    "title": "习近平同美国总统特朗普通电话",
    "url": "https://www.toutiao.com/article/7512475509360558619/",
    "label": ""
  },
  "items": [
    {
      "rank": 1,
      "title": "中美元首此次通话极为重要极不寻常",
      "url": "https://www.toutiao.com/trending/7576455726567017993/",
      "label": "hot"
    },
    {
      "rank": 2,
      "title": "神舟二十二号飞船今日发射",
      "url": "https://webcast-open.douyin.com/open/media_live/282773369501",
      "label": "new"
    },
    {
      "rank": 3,
      "title": "既重视中国经济 也重视中国人经济",
      "url": "https://www.toutiao.com/article/7576304511984190015",
      "label": ""
    },
    {
      "rank": 4,
      "title": "高市早苗与特朗普通话",
      "url": "https://www.toutiao.com/trending/7576254631207043118/",
      "label": "hot"
    },
    {
      "rank": 5,
      "title": "中国卫星拍下印战机坠毁现场",
      "url": "https://www.toutiao.com/trending/7575351925970059306/",
      "label": ""
    },
    {
      "rank": 6,
      "title": "净网 | 网警揭露直播间托儿真面目",
      "url": "https://www.toutiao.com/article/7576312131965043226",
      "label": ""
    },
    {
      "rank": 7,
      "title": "与特朗普通话谈及涉台言论？高市回应",
      "url": "https://www.toutiao.com/trending/7576495986903089178/",
      "label": "hot"
    },
    {
      "rank": 8,
      "title": "红旗车行驶中鸽子落车头成车标",
      "url": "https://www.toutiao.com/trending/7575172760805556270/",
      "label": ""
    },
    {
      "rank": 9,
      "title": "长征五号能将25吨重物一次推上太空",
      "url": "https://www.toutiao.com/trending/7575711374455062564/",
      "label": ""
    },
    {
      "rank": 10,
      "title": "特朗普：将于明年4月访华",
      "url": "https://www.toutiao.com/trending/7575503024580431379/",
      "label": ""
    },
    {
      "rank": 11,
      "title": "茅台辟谣加盟骗局",
      "url": "https://www.toutiao.com/trending/7576166726832754212/",
      "label": "refuteRumors"
    },
    {
      "rank": 12,
      "title": "陈百祥：中国一讲琉球独立日本就脚软",
      "url": "https://www.toutiao.com/trending/7575651677886251071/",
      "label": ""
    },
    {
      "rank": 13,
      "title": "NBA五支浴火重生球队你期待谁夺冠",
      "url": "https://www.toutiao.com/trending/7576101821702832147/",
      "label": "forum"
    },
    {
      "rank": 14,
      "title": "大鹅霸凌小狗崽遭报复活活咬死",
      "url": "https://www.toutiao.com/trending/7575439461274779684/",
      "label": ""
    },
    {
      "rank": 15,
      "title": "日本舆论担心高市言论进一步冲击经济",
      "url": "https://www.toutiao.com/trending/7576455955706039859/",
      "label": "hot"
    },
    {
      "rank": 16,
      "title": "意大利U17男足爆冷输球",
      "url": "https://www.toutiao.com/trending/7576211837701128198/",
      "label": "forum"
    },
    {
      "rank": 17,
      "title": "奇瑞新车规划曝光",
      "url": "https://www.toutiao.com/trending/7575514810545294884/",
      "label": "new"
    },
    {
      "rank": 18,
      "title": "直击西藏军区某部千人刺杀操大场面",
      "url": "https://www.toutiao.com/trending/7576136985921486899/",
      "label": "onSite"
    },
    {
      "rank": 19,
      "title": "境外势力利用看广告得奖励招募间谍",
      "url": "https://www.toutiao.com/trending/7576425299710345242/",
      "label": "new"
    },
    {
      "rank": 20,
      "title": "郑丽文中国人论述让沉默者不再沉默",
      "url": "https://www.toutiao.com/trending/7575737278471946303/",
      "label": "hot"
    },
    {
      "rank": 21,
      "title": "泽连斯基的政治前途恐随俄乌和平终结",
      "url": "https://www.toutiao.com/trending/7575533460346404902/",
      "label": "new"
    },
    {
      "rank": 22,
      "title": "鸠山由纪夫：中国批高市言论理所当然",
      "url": "https://www.toutiao.com/trending/7576351455515361316/",
      "label": ""
    },
    {
      "rank": 23,
      "title": "印度光辉战机坠毁吓跑4个意向购买国",
      "url": "https://www.toutiao.com/trending/7576440913648422438/",
      "label": ""
    },
    {
      "rank": 24,
      "title": "曝特朗普最后一刻才知28点计划内容",
      "url": "https://www.toutiao.com/trending/7575287851869323300/",
      "label": ""
    },
    {
      "rank": 25,
      "title": "中国稀土对西方到底有多重要",
      "url": "https://www.toutiao.com/trending/7576447875526168127/",
      "label": "new"
    },
    {
      "rank": 26,
      "title": "王毅对高市言论表态传递何信息",
      "url": "https://www.toutiao.com/trending/7576457529727651364/",
      "label": "interpretation"
    },
    {
      "rank": 27,
      "title": "香港撤销多场涉日活动",
      "url": "https://www.toutiao.com/trending/7575835387668430899/",
      "label": ""
    },
    {
      "rank": 28,
      "title": "郑丽文喊话“世代接棒”",
      "url": "https://www.toutiao.com/trending/7575865093238325286/",
      "label": "new"
    },
    {
      "rank": 29,
      "title": "河南鲁山8岁失联女孩姑姑发声",
      "url": "https://www.toutiao.com/trending/7576114217280618532/",
      "label": ""
    },
    {
      "rank": 30,
      "title": "王冰汝：万斯把鲁比奥坑惨了",
      "url": "https://www.toutiao.com/trending/7576460969530887689/",
      "label": ""
    },
    {
      "rank": 31,
      "title": "以色列违反停火协议400多次 中方发声",
      "url": "https://www.toutiao.com/trending/7575966336564592678/",
      "label": ""
    },
    {
      "rank": 32,
      "title": "全固态电池真的要“上车”了吗",
      "url": "https://www.toutiao.com/trending/7576432653063179819/",
      "label": ""
    },
    {
      "rank": 33,
      "title": "莫耶斯：频繁换帅背离了曼联价值观",
      "url": "https://www.toutiao.com/trending/7575602513154801670/",
      "label": "new"
    },
    {
      "rank": 34,
      "title": "眉山“偷甘蔗农场”爆火之后",
      "url": "https://www.toutiao.com/trending/7576182809401196563/",
      "label": ""
    },
    {
      "rank": 35,
      "title": "光辉在坠毁前尾部为何出现一缕白烟",
      "url": "https://www.toutiao.com/trending/7576465455775223359/",
      "label": "interpretation"
    },
    {
      "rank": 36,
      "title": "小米官方声明遭商场“反辟谣”",
      "url": "https://www.toutiao.com/trending/7575283076655218730/",
      "label": ""
    },
    {
      "rank": 37,
      "title": "中方回应日本将在台湾附近部署导弹",
      "url": "https://www.toutiao.com/trending/7576192078879706674/",
      "label": ""
    },
    {
      "rank": 38,
      "title": "陈小春儿子用三种语言主持校园活动",
      "url": "https://www.toutiao.com/trending/7576210109949952051/",
      "label": ""
    },
    {
      "rank": 39,
      "title": "高市早苗看莫迪的眼神耐人寻味",
      "url": "https://www.toutiao.com/trending/7575564483918889006/",
      "label": ""
    },
    {
      "rank": 40,
      "title": "邵永灵：特朗普成了“第二个拜登”",
      "url": "https://www.toutiao.com/trending/7576447344028159524/",
      "label": ""
    },
    {
      "rank": 41,
      "title": "“收留”不应成为欠薪借口",
      "url": "https://www.toutiao.com/trending/7575502881923629094/",
      "label": "new"
    },
    {
      "rank": 42,
      "title": "日本旅游业遇寒流酒店老板诉苦",
      "url": "https://www.toutiao.com/trending/7575704889323257910/",
      "label": "hot"
    },
    {
      "rank": 43,
      "title": "李在明称朝韩随时可能爆发冲突",
      "url": "https://www.toutiao.com/trending/7576427839524769307/",
      "label": ""
    },
    {
      "rank": 44,
      "title": "评论员：A股急跌后反弹信号明确",
      "url": "https://www.toutiao.com/trending/7576484526533119507/",
      "label": "new"
    },
    {
      "rank": 45,
      "title": "日本机场挤满了回国的人",
      "url": "https://www.toutiao.com/trending/7575269450723672083/",
      "label": "onSite"
    },
    {
      "rank": 46,
      "title": "若德罗赞进入市场 快船有意将其签下",
      "url": "https://www.toutiao.com/trending/7576210588700360745/",
      "label": "new"
    },
    {
      "rank": 47,
      "title": "杨瀚森垃圾时间登场2分钟无得分",
      "url": "https://www.toutiao.com/trending/7576358224505405482/",
      "label": "new"
    },
    {
      "rank": 48,
      "title": "9.9元“偷甘蔗”爆火 谁在花钱买罪受",
      "url": "https://www.toutiao.com/trending/7576442074493357609/",
      "label": ""
    },
    {
      "rank": 49,
      "title": "日本21万亿日元救市是“饮鸩止渴”吗",
      "url": "https://www.toutiao.com/trending/7576380473572868137/",
      "label": "new"
    },
    {
      "rank": 50,
      "title": "中方回应高市早苗称愿与中国进行对话",
      "url": "https://www.toutiao.com/trending/7575503024580202003/",
      "label": "hot"
    }
  ]
}